tudelft_pycar/__init__.py
tudelft_pycar/__main__.py
tudelft_pycar/arbiter.py
tudelft_pycar/path.py
tudelft_pycar/settings.py
tudelft_pycar/demo/main.py
tudelft_pycar/img/car.png
tudelft_pycar/img/microphone.png
tudelft_pycar/img/window-icon.png
tudelft_pycar/simulator/car.py
tudelft_pycar/simulator/main.py
tudelft_pycar/simulator/microphones.py
tudelft_pycar-0.0.6.dev0.dist-info/METADATA
tudelft_pycar-0.0.6.dev0.dist-info/WHEEL
tudelft_pycar-0.0.6.dev0.dist-info/licenses/LICENSE
tudelft_pycar-0.0.6.dev0.dist-info/RECORD
