Metadata-Version: 2.1
Name: tudelft_pycar
Version: 0.0.6.dev0
Summary: Support library for the 'EPO-4: "KITT" autonomous driving challenge' at Delft University of Technology
Project-URL: Homepage, https://gitlab.com/dstijns/epo4-python/
Project-URL: Bug Tracker, https://gitlab.com/dstijns/epo4-python/-/issues
Author-email: Anne Stijns <anstijns@gmail.com>
License-File: LICENSE
Classifier: License :: OSI Approved :: MIT License
Classifier: Operating System :: OS Independent
Classifier: Programming Language :: Python :: 3
Requires-Python: >=3.7
Requires-Dist: numpy
Requires-Dist: pyaudio~=0.2.12
Requires-Dist: pyglet~=2.0.4
Requires-Dist: pyserial~=3.5
